getcl.py
getcl-0.1.dist-info/LICENSE
getcl-0.1.dist-info/METADATA
getcl-0.1.dist-info/WHEEL
getcl-0.1.dist-info/entry_points.txt
getcl-0.1.dist-info/top_level.txt
getcl-0.1.dist-info/RECORD
