Metadata-Version: 2.1
Name: getcl
Version: 0.1
Summary: Python Package for the Mapping of Conceptlists
Home-page: https://github.com/lingpy/getcl/
Author: Johann-Mattis List
Author-email: mattis.list@uni-passau.de
License: MIT
Keywords: word prediction
Platform: any
Classifier: Programming Language :: Python
Classifier: Programming Language :: Python :: 3
Classifier: Programming Language :: Python :: 3.6
Classifier: Programming Language :: Python :: 3.7
Classifier: Programming Language :: Python :: 3.8
Classifier: Programming Language :: Python :: 3.9
Requires-Python: >=3.6
License-File: LICENSE
Requires-Dist: pysem >=0.5.0
Requires-Dist: pyconcepticon
Requires-Dist: cldfbench
Requires-Dist: tabulate
Requires-Dist: clldutils
Requires-Dist: pycldf
Provides-Extra: dev
Requires-Dist: wheel ; extra == 'dev'
Requires-Dist: twine ; extra == 'dev'
Provides-Extra: test
Requires-Dist: pytest >=4.3 ; extra == 'test'
Requires-Dist: pytest-cov ; extra == 'test'
Requires-Dist: coverage >=4.2 ; extra == 'test'
